netdevops_project/__init__.py
netdevops_project-0.1.0.dist-info/METADATA
netdevops_project-0.1.0.dist-info/WHEEL
netdevops_project-0.1.0.dist-info/RECORD
