Metadata-Version: 2.1
Name: netdevops-project
Version: 0.1.0
Summary: 
Author: Your Name
Author-email: you@example.com
Requires-Python: >=3.10,<4.0
Classifier: Programming Language :: Python :: 3
Classifier: Programming Language :: Python :: 3.10
Classifier: Programming Language :: Python :: 3.11
Requires-Dist: ansible (>=8.2.0,<9.0.0)
